arlulaapi/__init__.py
arlulaapi-1.4.0.dist-info/LICENSE
arlulaapi-1.4.0.dist-info/METADATA
arlulaapi-1.4.0.dist-info/WHEEL
arlulaapi-1.4.0.dist-info/top_level.txt
arlulaapi-1.4.0.dist-info/RECORD
