Metadata-Version: 2.1
Name: arlulaapi
Version: 1.4.0
Summary: A package to facilitate access to the Arlula Imagery Marketplace API
Home-page: https://github.com/Arlula/python-archive-sdk.git
Author: Adam Hamilton
Author-email: adamhammo99@gmail.com
License: UNKNOWN
Platform: UNKNOWN
Classifier: Programming Language :: Python :: 3
Classifier: License :: OSI Approved :: MIT License
Classifier: Operating System :: OS Independent
Requires-Dist: grequests
Requires-Dist: requests
Requires-Dist: pgeocode
Requires-Dist: arlulacore (==1.0.1)
